ccTopos/__init__.py
cctopos-0.0.1.dist-info/METADATA
cctopos-0.0.1.dist-info/WHEEL
cctopos-0.0.1.dist-info/licenses/LICENSE
cctopos-0.0.1.dist-info/RECORD
