Metadata-Version: 2.1
Name: ccTopos
Version: 0.0.1
Summary: Computing for climate change
Author-email: Lirong Yang <lirong.yang@outlook.com>
License-File: LICENSE
Classifier: License :: OSI Approved :: MIT License
Classifier: Operating System :: OS Independent
Classifier: Programming Language :: Python :: 3
Requires-Python: >=3.7
